{"type": "Feature", "id": 12512348, "geometry": {"type": "Point", "coordinates": [9.7097, 4.0133]}, "properties": {"woe:id": 12512348, "woe:parent_id": 1478198, "woe:name": "Douala Airport", "woe:placetype": 14, "woe:placetype_name": "Airport", "woe:lang": "ENG", "iso:country": "CM", "meta:provider": ["geoplanet:7.3.1", "geoplanet:7.3.2", "geoplanet:7.4.0", "geoplanet:7.4.1", "geoplanet:7.5.1", "geoplanet:7.5.2", "geoplanet:7.6.0", "geoplanet:7.8.1", "geoplanet:7.9.0", "geoplanet:7.10.0", "geoplanet:8.0.0", "woeplanet:8.0.0"], "meta:indexed": "2020-08-20T20:19:21.646070", "woe:alias_ENG_V": ["DLA Airport", "DLA"], "meta:updated": "2020-10-14T11:29:08.532992", "woe:hierarchy": {"continent": 24865670, "country": 23424785, "town": 0, "planet": 1, "county": 0, "suburb": 0, "state": 2345034, "region": 0, "localadmin": 0}, "woe:timezone_id": 28350699, "woe:hash": "s0wyufw7hmm5", "woe:centroid": [9.7097, 4.0133], "geom:latitude": 4.0133, "geom:longitude": 9.7097, "geom:hash": "s0wyufw7hmm5", "woe:latitude": 4.0133, "geom:centroid": [9.7097, 4.0133], "woe:longitude": 9.7097, "woe:repo": "woeplanet-airport-cm", "geom:area": 0.0, "woe:scale": 19}}